money_to_prisoners_common-21.2.0.dist-info/licenses/LICENSE
mtp_common/__init__.py
mtp_common/analytics.py
mtp_common/api.py
mtp_common/application_insights.py
mtp_common/apps.py
mtp_common/bank_accounts.py
mtp_common/context_processors.py
mtp_common/dates.py
mtp_common/logging.py
mtp_common/models.py
mtp_common/nomis.py
mtp_common/s3_bucket.py
mtp_common/screenshots.py
mtp_common/spooling.py
mtp_common/stack.py
mtp_common/tasks.py
mtp_common/utils.py
mtp_common/views.py
mtp_common/assets-src/mtp_common/_display.scss
mtp_common/assets-src/mtp_common/_index.scss
mtp_common/assets-src/mtp_common/_settings.scss
mtp_common/assets-src/mtp_common/_staff-app.scss
mtp_common/assets-src/mtp_common/_utils.scss
mtp_common/assets-src/mtp_common/index.js
mtp_common/assets-src/mtp_common/staff-app.js
mtp_common/assets-src/mtp_common/components/accordion/_index.scss
mtp_common/assets-src/mtp_common/components/accordion/index.js
mtp_common/assets-src/mtp_common/components/account-management/_index.scss
mtp_common/assets-src/mtp_common/components/analytics/index.js
mtp_common/assets-src/mtp_common/components/async-load/index.js
mtp_common/assets-src/mtp_common/components/autocomplete-select/_index.scss
mtp_common/assets-src/mtp_common/components/autocomplete-select/index.js
mtp_common/assets-src/mtp_common/components/before-unload/index.js
mtp_common/assets-src/mtp_common/components/breadcrumb-bar/_index.scss
mtp_common/assets-src/mtp_common/components/card/_index.scss
mtp_common/assets-src/mtp_common/components/card/index.js
mtp_common/assets-src/mtp_common/components/checkboxes/_index.scss
mtp_common/assets-src/mtp_common/components/cookie-banner/_index.scss
mtp_common/assets-src/mtp_common/components/cookie-banner/index.js
mtp_common/assets-src/mtp_common/components/date-picker/_index.scss
mtp_common/assets-src/mtp_common/components/date-picker/index.js
mtp_common/assets-src/mtp_common/components/dialogue-box/_index.scss
mtp_common/assets-src/mtp_common/components/dialogue-box/index.js
money_to_prisoners_common-21.2.0.dist-info/METADATA
money_to_prisoners_common-21.2.0.dist-info/WHEEL
money_to_prisoners_common-21.2.0.dist-info/top_level.txt
money_to_prisoners_common-21.2.0.dist-info/RECORD
