Metadata-Version: 2.4
Name: money-to-prisoners-common
Version: 21.2.0
Summary: Django app with common code and assets for Money to Prisoners services
Home-page: https://github.com/ministryofjustice/money-to-prisoners-common
Author: Ministry of Justice Digital Services
License: MIT
Classifier: Framework :: Django
Classifier: Intended Audience :: Developers
Classifier: License :: OSI Approved :: MIT License
Classifier: Operating System :: OS Independent
Classifier: Programming Language :: Python
Classifier: Programming Language :: Python :: 3
Classifier: Programming Language :: Python :: 3.12
Requires-Python: >=3.12
License-File: LICENSE
Requires-Dist: Django<5.3,>=5.2.7
Requires-Dist: django-widget-tweaks<1.6,>=1.5
Requires-Dist: notifications-python-client<11,>=10
Requires-Dist: requests~=2.32
Requires-Dist: requests-oauthlib~=2.0
Requires-Dist: slumber<0.8,>=0.7
Requires-Dist: selenium~=4.38
Requires-Dist: cryptography>=46
Requires-Dist: boto3~=1.40
Requires-Dist: kubernetes~=32.0
Requires-Dist: opencensus~=0.11
Requires-Dist: opencensus-ext-azure~=1.1
Requires-Dist: opencensus-ext-django~=0.8
Requires-Dist: prometheus-client~=0.23
Requires-Dist: sentry-sdk~=2.42
Requires-Dist: libsass~=0.23
Requires-Dist: uWSGI~=2.0.31
Requires-Dist: django-moj-irat==0.11
Requires-Dist: django-zendesk-tickets==0.19
Requires-Dist: govuk-bank-holidays==0.17
Provides-Extra: testing
Requires-Dist: flake8~=7.3; extra == "testing"
Requires-Dist: flake8-blind-except~=0.2.1; extra == "testing"
Requires-Dist: flake8-bugbear~=25.10; extra == "testing"
Requires-Dist: flake8-debugger~=4.1; extra == "testing"
Requires-Dist: flake8-quotes~=3.4; extra == "testing"
Requires-Dist: pep8-naming~=0.15; extra == "testing"
Requires-Dist: responses~=0.25; extra == "testing"
Requires-Dist: twine~=6.2; extra == "testing"
Requires-Dist: watchdog~=6.0; extra == "testing"
Dynamic: author
Dynamic: classifier
Dynamic: description
Dynamic: home-page
Dynamic: license
Dynamic: license-file
Dynamic: provides-extra
Dynamic: requires-dist
Dynamic: requires-python
Dynamic: summary
